{
    "csv": {
        "term": "09",
        "sessionPeriod": "01",
        "sessionTimes": "02",
        "meetingTimes": "",
        "billNo": "1050222070202600",
        "billName": "「立法院程序委員會組織規程部分條文修正草案」，請審議案。",
        "billOrg": "本院委員陳明文等23人",
        "billProposer": "陳明文　　",
        "billCosignatory": "趙正宇　　劉世芳　　林岱樺　　林俊憲　　李俊俋　　張廖萬堅　陳賴素　　何欣純　　吳思瑤　　鄭運鵬　　蘇治芬　　管碧玲　　蔡適應　　王定宇　　鄭寶清　　徐國勇　　陳　瑩　　",
        "billStatus": "審查完畢",
        "pdfUrl": "http://lci.ly.gov.tw/LyLCEW/agenda1/02/pdf/09/01/02/LCEWA01_090102_00089.pdf",
        "docUrl": "http://lci.ly.gov.tw/LyLCEW/agenda1/02/word/09/01/02/LCEWA01_090102_00089.doc",
        "selectTerm": "all"
    },
    "pdf": {
        "案由": "本院委員陳明文等 23 人，鑑於 2008 年至 2015 年立法院程序委員會濫用職權，阻撓杯葛各項改革議案的進行，地位儼然凌駕其他專業委員會，不符民意期待，爰提出「立法院程序委員會組織規程」部分條文修正草案。是否有當？提請公決。",
        "提案人": [
            "陳明文"
        ],
        "連署人": [
            "趙正宇",
            "劉世芳",
            "林岱樺",
            "林俊憲",
            "李俊俋",
            "張廖萬堅",
            "陳賴素美",
            "何欣純",
            "吳思瑤",
            "鄭運鵬",
            "蘇治芬",
            "管碧玲",
            "蔡適應",
            "王定宇",
            "鄭寶清",
            "徐國勇",
            "陳瑩",
            "蕭美琴",
            "陳曼麗",
            "邱議瑩",
            "谷辣斯．尤達卡Kolas Yotaka",
            "陳歐珀"
        ],
        "published_date": "2016-03-02",
        "提案號": "18321",
        "院總第": "23"
    }
}