{
    "csv": {
        "term": "09",
        "sessionPeriod": "02",
        "sessionTimes": "10",
        "meetingTimes": "",
        "billNo": "1051020070200100",
        "billName": "「公務人員退休法部分條文修正草案」，請審議案。",
        "billOrg": "本院委員蔡易餘等18人",
        "billProposer": "蔡易餘　　 ",
        "billCosignatory": "鄭寶清　　鄭運鵬　　段宜康　　黃秀芳　　吳焜裕Kolas Yotaka　　　　　李俊俋　　莊瑞雄　　陳明文　　陳曼麗　　黃國書　　施義芳　　洪宗熠　　何欣純　　鍾孔炤　　王定宇　　林俊憲　　",
        "billStatus": "交付審查",
        "pdfUrl": "http://lci.ly.gov.tw/LyLCEW/agenda1/02/pdf/09/02/08/LCEWA01_090208_00014.pdf",
        "docUrl": "http://lci.ly.gov.tw/LyLCEW/agenda1/02/word/09/02/08/LCEWA01_090208_00014.doc",
        "selectTerm": "all"
    },
    "pdf": {
        "案由": "本院委員蔡易餘等 18 人，有鑑於我國國人隨著醫療技術之進步，國民平均年齡大幅度提升，台灣社會已進入世界衛生組織（World Health Organization，以下簡稱 WHO）所認定之高齡化社會（aging society）標準。惟現行「公務人員退休法」規定：「公務員任職滿五年以上，年滿六十五歲者，應予屆齡退休。」，惟六十五歲之退休門檻以不符現今高齡化社會之需求，為因應人口結構之轉變，爰提出「公務人員退休法部分條文修正草案」。是否有當？敬請公決。說明：一、「公務人員退休法」自民過 36 年修正至今，退休年齡皆設定在 65 歲，惟我國國人平均年齡已逐漸趨向高齡化。根據內政部統計處所公布資料，民國 81 年國人平均年齡為 74.26 歲，民國 102 年度國人平均年齡為 80.02 歲，平均年齡有大幅提升之趨勢；但退休年齡仍維持不變，平均壽命延長，政府須支付公務人員更長時間的退休金，簡言之，隨著人口高齡化，政府必須支付更多資源於退撫機制。二、根據中華民國統計資訊網 2015 年社會指標統計年報指出，2011 年我國健康平均餘命為 72.6歲，與平均壽命相較，不健康存活年數為 6.6 年，與 2001 年相較，十年來健康平均餘命提高 2.2 歲。建康平均餘命提高亦代表，能提供勞動力服務之年齡也隨之提高。三、依據行政院主計處之人口推估，我國人口成長將在近幾年出現負成長的現象，其後隨著人口老化，人口成長率將持續下降。若未來的勞動參與率維持在目前的水準，總產出將因人口結構的變化而產生長期下降的趨勢。依據經建會的人口推估資料，分析人口高齡化對經濟成長的影響，並模擬可能減緩對產出不利衝擊的因素，結果顯示持續提升生育率、提升勞動就業率，以及提高勞動參與率、延遲退休年齡等，均可減緩人口老化的不利衝擊。四、日本為因應高齡化社會而積極採取因應的對策，首先於 1995 年制定「高齡社會對策基本法」，2001 年制定「高齡社會對策大綱」，更於 2006 年 4 月立法實施「改正高年齡者僱用安定法」，規定企業必須對高齡者實施：(1)延長退休年齡，(2)延長僱用，(3)廢止退休制度三者擇一的措施，以確保高齡者的僱用。五、「公務人員法」第五條規定之屆齡退休之認定，原條文（2010 年前條文）保有可延後退休之規定。但 2010 年經歷一次全文修正，將可延後退休之規定取消，造成公務人員在年滿 65歲時必須強迫退休，惟修正僅依年齡作為區隔，未考量到個別公務員延續工作之可行性，爰於條文中新增可申請「延後退休」之規定。",
        "提案人": [
            "蔡易餘"
        ],
        "連署人": [
            "鄭寶清",
            "鄭運鵬",
            "段宜康",
            "黃秀芳",
            "吳焜裕",
            "谷辣斯．尤達卡Kolas Yotaka",
            "李俊俋",
            "莊瑞雄",
            "陳明文",
            "陳曼麗",
            "黃國書",
            "施義芳",
            "洪宗熠",
            "何欣純",
            "鍾孔炤",
            "王定宇",
            "林俊憲"
        ],
        "published_date": "2016-10-26",
        "提案號": "19673",
        "院總第": "234"
    }
}