{
    "csv": {
        "term": "09",
        "sessionPeriod": "02",
        "sessionTimes": "21",
        "meetingTimes": "",
        "billNo": "1051128070201100",
        "billName": "「入出國及移民法第二十三條及第二十五條條文修正草案」，請審議案。",
        "billOrg": "本院委員許毓仁等19人",
        "billProposer": "許毓仁　　林麗蟬　　 ",
        "billCosignatory": "楊鎮浯　　柯志恩　　廖國棟　　曾銘宗　　簡東明　　呂玉玲　　賴士葆　　徐志榮　　徐榛蔚　　馬文君　　陳學聖　　羅明才　　林為洲　　林德福　　許淑華　　黃昭順　　周陳秀霞　　　　　　",
        "billStatus": "交付審查",
        "pdfUrl": "http://lci.ly.gov.tw/LyLCEW/agenda1/02/pdf/09/02/14/LCEWA01_090214_00019.pdf",
        "docUrl": "http://lci.ly.gov.tw/LyLCEW/agenda1/02/word/09/02/14/LCEWA01_090214_00019.doc",
        "selectTerm": "all"
    },
    "pdf": {
        "案由": "本院委員許毓仁、林麗蟬等 19 人，專業外國人士申請取得永久居留權後，為使其在台全心工作、貢獻所長，免於配偶、子女等家人受限移民法規，為免影響在台工作意願，遂增加配偶、子女隨同取得永久居留之權益。以保障專業外國人在台工作之家庭團聚的基本人權。現行在台居留工作之外籍白領人士，已有身心障礙無法自理之成年子女，有共同生活之必要，為免於外籍白領生活工作之不便，以及基於人道之考量。爰修正入出國及移民法第二十三條及第二十五條條文。是否有當？敬請公決。說明：一、專業外國人士申請取得永久居留權後，為使其在台全心工作、貢獻所長，免於配偶、子女等家人受限移民法規，為免影響在台工作意願，遂增加配偶、子女隨同取得永久居留之權益。以保障專業外國人在台工作之家庭團聚的基本人權。二、現行在台居留工作之外籍白領人士，已有身心障礙無法自理之成年子女，有共同生活之必要，為免於外籍白領生活工作之不便，以及基於人道之考量。",
        "提案人": [
            "許毓仁",
            "林麗蟬"
        ],
        "連署人": [
            "楊鎮浯",
            "柯志恩",
            "廖國棟",
            "曾銘宗",
            "簡東明",
            "呂玉玲",
            "賴士葆",
            "徐志榮",
            "徐榛蔚",
            "馬文君",
            "陳學聖",
            "羅明才",
            "林為洲",
            "林德福",
            "許淑華",
            "黃昭順",
            "周陳秀霞"
        ],
        "published_date": "2016-12-07",
        "提案號": "19957",
        "院總第": "1684"
    }
}