{
    "csv": {
        "term": "09",
        "sessionPeriod": "02",
        "sessionTimes": "17",
        "meetingTimes": "",
        "billNo": "1051226070200200",
        "billName": "「道路交通管理處罰條例第九十二條條文修正草案」，請審議案。",
        "billOrg": "本院委員林昶佐等16人",
        "billProposer": "",
        "billCosignatory": "",
        "billStatus": "交付審查",
        "pdfUrl": "http://lci.ly.gov.tw/LyLCEW/agenda1/02/pdf/09/02/17/LCEWA01_090217_00302.pdf",
        "docUrl": "http://lci.ly.gov.tw/LyLCEW/agenda1/02/word/09/02/17/LCEWA01_090217_00302.doc",
        "selectTerm": "all"
    },
    "pdf": {
        "案由": "本院委員林昶佐、蔡適應等 16 人，鑑於本院已於 2011 年通過「道路交通管理處罰條例」修正案，明訂汽缸排氣量五百五十立方公分以上大型重型機車，得依交通部公告規定之路段及時段行駛高速公路，並於附帶決議建請交通部以國 6、國8 以及國 3 新化以南路段優先試辦，在安全性及風險有效控管原則下，分階段規劃可開放之路段及時段；然至今仍遲未進行，顯與附帶決議精神不符。為避免行政怠惰，爰此增訂相關資訊公開機制，特擬具「道路交通管理處罰條例第九十二條條文修正草案」。是否有當？敬請公決。說明：一、鑑於立法院已於 2011 年 11 月 8 號通過「道路交通管理處罰條例第九十二條條文修正案」明訂汽缸排氣量五百五十立方公分以上大型重型機車得依交通部公告規定之路段及時段行駛高速公路，並通過附帶決議「建請以國 6 國 8 及國 3 新化以南路段為優先試辦路段……，鑑於社會各界對於開放 550c.c.以上大型重型機車行駛高速公路，存有安全之疑慮，授權由交通部應在安全性及風險有效控管原則下，分階段規劃可開放之路段及時段。」，賦予交通部行政裁量權，並責成交通部辦理重型機車行駛國道試辦，視成效與影響分階段逐步規劃可開放之路段與時段。二、然而從 2011 年至今五年，交通部僅開放國 3 甲台北至深坑端總長 5.6 公里路段，未進行其他路段之試辦，亦未進行道路設施、交通號誌等工程與其他相關配套規劃推動，僅進行三次民眾對開放重型機車行駛國道意向調查，未實際試辦以評估成效與影響，顯與附帶決議精神不符，恐有行政怠惰之虞。三、重型機車行駛國道之規劃，交通部除了搜集民眾意見，更應以實際試辦數據成果評估安全性與風險，方能實際掌握重型機車行駛國道狀況，妥適保障民眾道路使用權益。四、因攸關政府資訊公開與民眾資訊知情權，避免社會資源浪費與民眾預期等待心理，爰此，於本法第九十二條中明訂交通部應定期公告重型機車得行駛之國道路段、時段與評估規劃，以期交通部積極處理試辦並公開評估報告與未來規劃，以利政府資訊公開，落實社會溝通。",
        "提案人": [
            "林昶佐",
            "蔡適應"
        ],
        "連署人": [
            "何欣純",
            "陳超明",
            "徐志榮",
            "陳其邁",
            "蘇巧慧",
            "姚文智",
            "高潞．以用．巴魕剌Kawlo．Iyun．Pacidal",
            "許毓仁",
            "徐永明",
            "呂孫綾",
            "洪慈庸",
            "高志鵬",
            "尤美女",
            "黃國昌"
        ],
        "published_date": "2016-12-30",
        "提案號": "20163",
        "院總第": "756"
    }
}