{
    "csv": {
        "term": "09",
        "sessionPeriod": "02",
        "sessionTimes": "10",
        "meetingTimes": "",
        "billNo": "1051102070200400",
        "billName": "「勞動基準法第三十八條條文修正草案」，請審議案。",
        "billOrg": "本院委員張廖萬堅等20人",
        "billProposer": "張廖萬堅　 ",
        "billCosignatory": "吳思瑤　　黃國書　　許智傑　　李麗芬　　蘇巧慧　　吳琪銘　　李俊俋　　賴瑞隆　　劉櫂豪　　陳歐珀　　趙正宇　　郭正亮　　呂孫綾　　林靜儀　　蔡易餘　　陳明文　　吳焜裕　　陳賴素美　",
        "billStatus": "交付審查",
        "pdfUrl": "http://lci.ly.gov.tw/LyLCEW/agenda1/02/pdf/09/02/10/LCEWA01_090210_00027.pdf",
        "docUrl": "http://lci.ly.gov.tw/LyLCEW/agenda1/02/word/09/02/10/LCEWA01_090210_00027.doc",
        "selectTerm": "all"
    },
    "pdf": {
        "案由": "本院委員張廖萬堅等 19 人，根據現行法，勞工休假型態有三：「例假」（每周七日之一日）、「休假」（紀念日、勞動節日等）與「特別休假」（同一雇主且繼續工作滿一定年資）。其中關於「特別休假」的休假日期，未如例假或休假明確或固定，而是由勞資雙方協商排定，但因現行法未明定行使特別休假權之原則規定，致使特別休假僅有形式上的意義（看得到、卻吃不到），無助於減緩我國勞工工時過長問題，爰此，提出「勞動基準法第三十八條」條文修正草案，特別休假勞工不得拋棄、雇主或事業單位除有符合法規定加發工資工作或事後補假休息外不得拒絕，特別休假因年度終結或終止契約而未休者，其應休未休之日數，雇主應發給工資，以健全特別休假制度。是否有當？敬請公決。",
        "提案人": [
            "張廖萬堅"
        ],
        "連署人": [
            "吳思瑤",
            "黃國書",
            "許智傑",
            "李麗芬",
            "蘇巧慧",
            "吳琪銘",
            "李俊俋",
            "賴瑞隆",
            "劉櫂豪",
            "陳歐珀",
            "趙正宇",
            "郭正亮",
            "呂孫綾",
            "林靜儀",
            "蔡易餘",
            "陳明文",
            "吳焜裕",
            "陳賴素美"
        ],
        "published_date": "2016-11-09",
        "提案號": "19774",
        "院總第": "1121"
    }
}