{
    "csv": {
        "term": "09",
        "sessionPeriod": "02",
        "sessionTimes": "16",
        "meetingTimes": "",
        "billNo": "1051212070200100",
        "billName": "「海洋及漁業部航港署組織法草案」，請審議案。",
        "billOrg": "本院委員姚文智等19人",
        "billProposer": "姚文智　　陳其邁　　葉宜津　　賴瑞隆　　莊瑞雄　　陳曼麗　　呂孫綾　　趙天麟　　 ",
        "billCosignatory": "李俊俋　　吳琪銘　　洪宗熠　　楊　曜　　何欣純　　邱議瑩　　施義芳　　Kolas Yotaka　　　　 黃秀芳　　李麗芬　　洪慈庸　　",
        "billStatus": "交付審查",
        "pdfUrl": "http://lci.ly.gov.tw/LyLCEW/agenda1/02/pdf/09/02/16/LCEWA01_090216_00008.pdf",
        "docUrl": "http://lci.ly.gov.tw/LyLCEW/agenda1/02/word/09/02/16/LCEWA01_090216_00008.doc",
        "selectTerm": "all"
    },
    "pdf": {
        "案由": "本院委員姚文智、陳其邁、葉宜津、賴瑞隆、莊瑞雄、陳曼麗、呂孫綾、趙天麟等 19 人，鑑於船舶、港口、航務、海運等業務，與海洋觀光產業發展息息相關，亦與漁業署所管理之漁港、漁船、釣魚採捕載具關係密切，應納入同一海洋事務主管機關共同管理協調。未來配合發展海洋休閒觀光產業，遊艇港之投資與管理業務可預期將會日重，加上部內「司」數量有限，部內能量應保留彈性以備用於缺乏次級機關之新興海洋業務上。故應將航港局納入海洋及漁業部，並改制為航港署。爰擬具「海洋及漁業部航港署組織法」草案。是否有當？敬請公決。",
        "提案人": [
            "姚文智",
            "陳其邁",
            "葉宜津",
            "賴瑞隆",
            "莊瑞雄",
            "陳曼麗",
            "呂孫綾",
            "趙天麟"
        ],
        "連署人": [
            "李俊俋",
            "吳琪銘",
            "洪宗熠",
            "楊曜",
            "何欣純",
            "邱議瑩",
            "施義芳",
            "谷辣斯．尤達卡Kolas Yotaka",
            "黃秀芳",
            "李麗芬",
            "洪慈庸"
        ],
        "published_date": "2016-12-21",
        "提案號": "20042",
        "院總第": "1603"
    }
}