{
    "csv": {
        "term": "09",
        "sessionPeriod": "02",
        "sessionTimes": "07",
        "meetingTimes": "",
        "billNo": "1051012070200100",
        "billName": "「立法院職權行使法部分條文修正草案」，請審議案。",
        "billOrg": "本院時代力量黨團",
        "billProposer": "",
        "billCosignatory": "",
        "billStatus": "審查完畢",
        "pdfUrl": "http://lci.ly.gov.tw/LyLCEW/agenda1/02/pdf/09/02/07/LCEWA01_090207_00009.pdf",
        "docUrl": "http://lci.ly.gov.tw/LyLCEW/agenda1/02/word/09/02/07/LCEWA01_090207_00009.doc",
        "selectTerm": "all"
    },
    "pdf": {
        "案由": "本院時代力量黨團，有鑑於立法委員係由人民直接選舉發生，其職權亦來自於人民之授權，立法委員本應憑其智識及信念，依人民之理念與利益行動，以盡選民藉由選舉所託付之義務。然而，立法院長期以來之職權行使，因黨團協商制度導致議事程序空洞化，除立法品質未盡符合人民之期待，議事運作亦有欠透明，致選民難以監督、追究立法委員之政治責任。為達成立法專業化及議事透明化之改革目標，爰提案修正立法院職權行使法部分條文，將黨團協商限縮於程序性事項、增加委員會將所審查之法律案提報院會之程序限制，並新增政黨辯論程序。是否有當？敬請公決。",
        "提案人": [
            "時代力量立法院黨團",
            "黃國昌",
            "林昶佐",
            "徐永明"
        ],
        "連署人": [],
        "published_date": "2016-10-19",
        "提案號": "19646",
        "院總第": "23"
    }
}