{
    "csv": {
        "term": "09",
        "sessionPeriod": "03",
        "sessionTimes": "04",
        "meetingTimes": "",
        "billNo": "1060302070200700",
        "billName": "「國家公園法部分條文修正草案」，請審議案。",
        "billOrg": "本院委員Kolas Yotaka等22人",
        "billProposer": "Kolas Yotaka　　　　 鍾佳濱　　 ",
        "billCosignatory": "李俊俋　　鍾孔炤　　陳其邁　　林俊憲　　吳焜裕　　趙天麟　　段宜康　　邱志偉　　李麗芬　　姚文智　　郭正亮　　吳琪銘　　林靜儀　　陳曼麗　　吳玉琴　　許智傑　　邱泰源　　洪宗熠　　鄭寶清　　蔡易餘　　",
        "billStatus": "交付審查",
        "pdfUrl": "http://lci.ly.gov.tw/LyLCEW/agenda1/02/pdf/09/03/04/LCEWA01_090304_00025.pdf",
        "docUrl": "http://lci.ly.gov.tw/LyLCEW/agenda1/02/word/09/03/04/LCEWA01_090304_00025.doc",
        "selectTerm": "all"
    },
    "pdf": {
        "案由": "本院委員 Kolas Yotaka、鍾佳濱等 22 人，鑑於國家公園法自六十一年制定以來，從未考量原居住國家公園區域內原住民族之基本生計，嚴重影響居民生存及居住權益甚鉅。參照先進國家之治理方式，劃設範圍涉及當地原住民族之傳統領域，皆有與其成立共同管理委員會之先例。為衡平當地原住民族基本權益與保護自然資源之利益，重新修正「國家公園法」，以達共存共榮雙贏局面。是否有當？敬請公決。說明：本法僅於九十九年就國家公園之選定基準及其定義等相關事項修正。惟就實務上常見之當地原住民族基本權利侵害爭議以及當地原住民族無法實際參與相關區域之劃定與變更之問題，未見通盤檢討，並重新修補國家公園與當地居民之關係，爰擬具本法修正草案，其修正要點如下：(一)劃設範圍涉及原住民族地區，增列主管機關為原住民族委員會。(二)國家公園之劃設應納入當地居民之意見，修正國家公園計畫委員會應有一定比例之原住民委員名額。(三)明文規範範圍涉及原住民族地區之國家公園，應與當地原住民族建立共同管理機制，並要求具原住民身分之委員應有一定比例，共同管理國家公園治理。(四)明文規範當地原住民族基於傳統文化、祭儀或自用等微量使用非營利可行使之傳統權利事項，並賦予一定保育國家公園自然資源之責任。",
        "提案人": [
            "谷辣斯．尤達卡Kolas Yotaka",
            "鍾佳濱"
        ],
        "連署人": [
            "李俊俋",
            "鍾孔炤",
            "陳其邁",
            "林俊憲",
            "吳焜裕",
            "趙天麟",
            "段宜康",
            "邱志偉",
            "李麗芬",
            "姚文智",
            "郭正亮",
            "吳琪銘",
            "林靜儀",
            "陳曼麗",
            "吳玉琴",
            "許智傑",
            "邱泰源",
            "洪宗熠",
            "鄭寶清",
            "蔡易餘"
        ],
        "published_date": "2017-03-08",
        "提案號": "20277",
        "院總第": "866"
    }
}