{
    "csv": {
        "term": "09",
        "sessionPeriod": "04",
        "sessionTimes": "15",
        "meetingTimes": "",
        "billNo": "1061222070200700",
        "billName": "「職能治療師法第三條條文修正草案」，請審議案。",
        "billOrg": "本院委員何欣純等18人",
        "billProposer": "",
        "billCosignatory": "",
        "billStatus": "交付審查",
        "pdfUrl": "http://lci.ly.gov.tw/LyLCEW/agenda1/02/pdf/09/04/15/LCEWA01_090415_00051.pdf",
        "docUrl": "http://lci.ly.gov.tw/LyLCEW/agenda1/02/word/09/04/15/LCEWA01_090415_00051.doc",
        "selectTerm": "all"
    },
    "pdf": {
        "案由": "本院委員何欣純等 18 人，自 101 年行政院組織改造開始施行，「衛生福利部組織法」於 102 年制定完成後開始施行，行政院衛生署正式改組為「衛生福利部」，為我國最高衛生及社會福利行政機關，負責全國衛生及社會福利行政事務。然法規內容中針對主管機關卻未隨之調整，為完備法制程序，爰提出「職能治療師法第三條條文修正草案」，將該法所稱主管機關由衛生署修正為衛生福利部。是否有當？敬請公決。說明：102 年 5 月 31 日「衛生福利部組織法」制定，102 年 7 月 23 日正式施行，將「行政院衛生署」改組為「衛生福利部」，然而法規中針對主管機關之條文未隨之調整，為完備法制程序且避免民眾混淆，爰提出「職能治療師法第三條修正草案」。",
        "提案人": [
            "何欣純"
        ],
        "連署人": [
            "鍾孔炤",
            "陳賴素美",
            "黃秀芳",
            "許智傑",
            "蔡易餘",
            "鍾佳濱",
            "邱泰源",
            "趙正宇",
            "洪宗熠",
            "李麗芬",
            "蕭美琴",
            "蔡適應",
            "蘇巧慧",
            "谷辣斯．尤達卡Kolas Yotaka",
            "呂孫綾",
            "吳焜裕",
            "鄭寶清"
        ],
        "published_date": "2017-12-27",
        "提案號": "21585",
        "院總第": "1573"
    }
}