{
    "csv": {
        "term": "09",
        "sessionPeriod": "05",
        "sessionTimes": "07",
        "meetingTimes": "",
        "billNo": "1070331070201400",
        "billName": "「全民健康保險法第一條條文修正草案」，請審議案。",
        "billOrg": "本院委員陳宜民等16人",
        "billProposer": "陳宜民　　",
        "billCosignatory": "許淑華　　林為洲　　鄭天財Sra Kacaw　　 孔文吉　　王育敏　　蔣乃辛　　蔣萬安　　許毓仁　　吳志揚　　林德福　　楊鎮浯　　柯志恩　　黃昭順　　羅明才　　林麗蟬　　",
        "billStatus": "交付審查",
        "pdfUrl": "http://lci.ly.gov.tw/LyLCEW/agenda1/02/pdf/09/05/07/LCEWA01_090507_00071.pdf",
        "docUrl": "http://lci.ly.gov.tw/LyLCEW/agenda1/02/word/09/05/07/LCEWA01_090507_00071.doc",
        "selectTerm": "all"
    },
    "pdf": {
        "案由": "本院委員陳宜民等 16 人，有鑑於「預防勝於治療」是大家所熟知，透過先進有效地疫苗接種，將可減少事後的醫療支出與民眾生命的傷亡。爰擬具「全民健康保險法第一條條文修正草案」，以前端、治本及預防之具體作法，改善民眾健康情形，以減少後端之健保負擔。是否有當？敬請公決。",
        "提案人": [
            "陳宜民"
        ],
        "連署人": [
            "許淑華",
            "林為洲",
            "鄭天財Sra．Kacaw",
            "孔文吉",
            "王育敏",
            "蔣乃辛",
            "蔣萬安",
            "許毓仁",
            "吳志揚",
            "林德福",
            "楊鎮浯",
            "柯志恩",
            "黃昭順",
            "羅明才",
            "林麗蟬"
        ],
        "published_date": "2018-04-04",
        "提案號": "21832",
        "院總第": "1604"
    }
}