{
    "csv": {
        "term": "09",
        "sessionPeriod": "05",
        "sessionTimes": "14",
        "meetingTimes": "",
        "billNo": "1070518070200800",
        "billName": "「性別工作平等法第十七條條文修正草案」，請審議案。",
        "billOrg": "本院委員賴瑞隆等20人",
        "billProposer": "賴瑞隆　　洪慈庸　　江永昌　　尤美女　　",
        "billCosignatory": "Kolas Yotaka　　 邱議瑩　　李俊俋　　邱泰源　　",
        "billStatus": "交付審查",
        "pdfUrl": "http://lci.ly.gov.tw/LyLCEW/agenda1/02/pdf/09/05/14/LCEWA01_090514_00062.pdf",
        "docUrl": "http://lci.ly.gov.tw/LyLCEW/agenda1/02/word/09/05/14/LCEWA01_090514_00062.doc",
        "selectTerm": "all"
    },
    "pdf": {
        "案由": "本院委員賴瑞隆、洪慈庸、江永昌、尤美女等 20 人，為保障受僱者勞動權益及因應少子化社會來臨，受僱者申請育嬰留職停薪期滿申請復職時，雇主除不得拒絕外，亦應不得降低其原有之相關勞動條件，俾實質保障受僱者工作權，爰擬具「性別工作平等法第十七條條文修正草案」。是否有當？敬請公決。說明：受僱者申請育嬰留職停薪之因素眾多，然其出發點多是以照顧嬰幼兒為主，在少子化時代亦不得不然，故法律對於受僱者申請育嬰留職停薪期滿後，申請復職之保障須更加周密嚴謹，以降低對受僱者勞動權益之傷害，並完善育嬰留職停薪機制。一般不肖雇主，對育嬰留職停薪期滿申請復職之受僱者常做出之情事包括：降低薪資、不當調離原工作地點以及苛扣休假等情況，故為完善性別工作平等法第十七條，擬具修正條文。",
        "提案人": [
            "賴瑞隆",
            "洪慈庸",
            "江永昌",
            "尤美女"
        ],
        "連署人": [
            "谷辣斯．尤達卡Kolas Yotaka",
            "邱議瑩",
            "李俊俋",
            "邱泰源",
            "邱志偉",
            "陳曼麗",
            "蔡易餘",
            "黃偉哲",
            "吳焜裕",
            "陳瑩",
            "林靜儀",
            "張廖萬堅",
            "鍾佳濱",
            "何欣純",
            "呂孫綾",
            "劉建國"
        ],
        "published_date": "2018-05-23",
        "提案號": "22189",
        "院總第": "1542"
    }
}